remote_kernel/__init__.py
remote_kernel/__main__.py
remote_kernel/_version.py
remote_kernel/dialog.py
remote_kernel/install.py
remote_kernel/ssh_client.py
remote_kernel/start.py
remote_kernel/sync.py
remote_kernel/resources/logo-32x32.png
remote_kernel/resources/logo-64x64.png
remote_kernel-1.1.dist-info/LICENSE.txt
remote_kernel-1.1.dist-info/METADATA
remote_kernel-1.1.dist-info/WHEEL
remote_kernel-1.1.dist-info/top_level.txt
remote_kernel-1.1.dist-info/RECORD
