Metadata-Version: 2.1
Name: remote_kernel
Version: 1.1
Summary: Python Script to connect to remote IPyKernel via ssh
Home-page: UNKNOWN
Author: Joost van Griethuysen
Author-email: joostjm@gmail.com
License: BSD License
Keywords: remote-kernel,ipykernel,ssh
Platform: UNKNOWN
Classifier: Development Status :: 1 - Planning
Classifier: Environment :: Console
Classifier: Intended Audience :: Developers
Classifier: License :: OSI Approved :: BSD License
Classifier: Operating System :: Microsoft :: Windows
Classifier: Programming Language :: Python :: 3
Classifier: Programming Language :: Python :: 3.5
Classifier: Topic :: Utilities
